wmwpy/__init__.py
wmwpy/game.py
wmwpy/gameobject.py
wmwpy/gametemplate.py
wmwpy/Font/__init__.py
wmwpy/classes/Widgets.py
wmwpy/classes/__init__.py
wmwpy/classes/curves.py
wmwpy/classes/database.py
wmwpy/classes/imagelist.py
wmwpy/classes/layout.py
wmwpy/classes/level.py
wmwpy/classes/location.py
wmwpy/classes/object.py
wmwpy/classes/sprite.py
wmwpy/classes/texture.py
wmwpy/classes/texturesettings.py
wmwpy/classes/objectpack/__init__.py
wmwpy/classes/objectpack/pack.py
wmwpy/classes/objectpack/type.py
wmwpy/classes/widget/WT_CANVAS.py
wmwpy/classes/widget/WT_FINGER_CATCHER.py
wmwpy/classes/widget/WT_GROUP.py
wmwpy/classes/widget/WT_ICON_LIST.py
wmwpy/classes/widget/WT_LABEL.py
wmwpy/classes/widget/WT_PROGRESS_BAR.py
wmwpy/classes/widget/WT_PUSH_BUTTON.py
wmwpy/classes/widget/WT_SCROLLABLE_CAMERA.py
wmwpy/classes/widget/WT_SCROLLABLE_SET.py
wmwpy/classes/widget/WT_SLIDER.py
wmwpy/classes/widget/WT_TOGGLE.py
wmwpy/classes/widget/__init__.py
wmwpy/classes/widget/widget.py
wmwpy/object_packs/WMW.py
wmwpy/object_packs/__init__.py
wmwpy/utils/XMLTools.py
wmwpy/utils/__init__.py
wmwpy/utils/color.py
wmwpy/utils/filesystem.py
wmwpy/utils/gif.py
wmwpy/utils/imageprocessing.py
wmwpy/utils/path.py
wmwpy/utils/rotate.py
wmwpy/utils/textures.py
wmwpy/utils/waltex.py
wmwpy/utils/file_types/Documents.py
wmwpy/utils/file_types/Images.py
wmwpy/utils/file_types/__init__.py
wmwpy-0.6.0b0.dist-info/LICENSE
wmwpy-0.6.0b0.dist-info/METADATA
wmwpy-0.6.0b0.dist-info/WHEEL
wmwpy-0.6.0b0.dist-info/top_level.txt
wmwpy-0.6.0b0.dist-info/RECORD
