Metadata-Version: 2.1
Name: wmwpy
Version: 0.6.0b0
Summary: Python module to work with files in the Where's My Water? mobile game series.
Author: ego-lay-atman-bay
License: GNU GENERAL PUBLIC LICENSE
Project-URL: Homepage, https://github.com/wmw-modding/wmwpy
Project-URL: Bug Tracker, https://github.com/wmw-modding/wmwpy/issues
Project-URL: Documentation, https://wmw-modding.github.io/wmwpy/
Classifier: Programming Language :: Python :: 3
Classifier: License :: OSI Approved :: GNU General Public License v3 (GPLv3)
Classifier: Operating System :: OS Independent
Requires-Python: >=3.11
License-File: LICENSE
Requires-Dist: lxml
Requires-Dist: numpy
Requires-Dist: Pillow
Requires-Dist: natsort
Requires-Dist: filetype
